catseye/__init__.py
catseye-0.0.1.dist-info/METADATA
catseye-0.0.1.dist-info/RECORD
catseye-0.0.1.dist-info/WHEEL
catseye-0.0.1.dist-info/top_level.txt
