Metadata-Version: 2.1
Name: catseye
Version: 0.0.1
Summary: 猫眼
Home-page: https://test.com
Author: jthmath
Author-email: jthmath@vip.163.com
License: UNKNOWN
Platform: UNKNOWN
